{
  "openapi": "3.0.1",
  "info": {
    "title": "my-web-api",
    "version": "1.0"
  },
  "paths": {
    "/api/About": {
      "get": {
        "tags": [
          "About"
        ],
        "responses": {
          "200": {
            "description": "OK"
          }
        }
      },
      "post": {
        "tags": [
          "About"
        ],
        "requestBody": {
          "content": {
            "application/json": {
              "schema": {
                "$ref": "#/components/schemas/AboutMe"
              }
            },
            "text/json": {
              "schema": {
                "$ref": "#/components/schemas/AboutMe"
              }
            },
            "application/*+json": {
              "schema": {
                "$ref": "#/components/schemas/AboutMe"
              }
            }
          }
        },
        "responses": {
          "200": {
            "description": "OK"
          }
        }
      },
      "put": {
        "tags": [
          "About"
        ],
        "parameters": [
          {
            "name": "id",
            "in": "query",
            "schema": {
              "type": "integer",
              "format": "int32"
            }
          }
        ],
        "requestBody": {
          "content": {
            "application/json": {
              "schema": {
                "$ref": "#/components/schemas/AboutMe"
              }
            },
            "text/json": {
              "schema": {
                "$ref": "#/components/schemas/AboutMe"
              }
            },
            "application/*+json": {
              "schema": {
                "$ref": "#/components/schemas/AboutMe"
              }
            }
          }
        },
        "responses": {
          "200": {
            "description": "OK"
          }
        }
      },
      "delete": {
        "tags": [
          "About"
        ],
        "parameters": [
          {
            "name": "id",
            "in": "query",
            "schema": {
              "type": "integer",
              "format": "int32"
            }
          }
        ],
        "responses": {
          "200": {
            "description": "OK"
          }
        }
      }
    },
    "/api/Education": {
      "get": {
        "tags": [
          "Education"
        ],
        "responses": {
          "200": {
            "description": "OK"
          }
        }
      },
      "post": {
        "tags": [
          "Education"
        ],
        "requestBody": {
          "content": {
            "application/json": {
              "schema": {
                "$ref": "#/components/schemas/Education"
              }
            },
            "text/json": {
              "schema": {
                "$ref": "#/components/schemas/Education"
              }
            },
            "application/*+json": {
              "schema": {
                "$ref": "#/components/schemas/Education"
              }
            }
          }
        },
        "responses": {
          "200": {
            "description": "OK"
          }
        }
      },
      "put": {
        "tags": [
          "Education"
        ],
        "parameters": [
          {
            "name": "id",
            "in": "query",
            "schema": {
              "type": "integer",
              "format": "int32"
            }
          }
        ],
        "requestBody": {
          "content": {
            "application/json": {
              "schema": {
                "$ref": "#/components/schemas/Education"
              }
            },
            "text/json": {
              "schema": {
                "$ref": "#/components/schemas/Education"
              }
            },
            "application/*+json": {
              "schema": {
                "$ref": "#/components/schemas/Education"
              }
            }
          }
        },
        "responses": {
          "200": {
            "description": "OK"
          }
        }
      },
      "delete": {
        "tags": [
          "Education"
        ],
        "parameters": [
          {
            "name": "id",
            "in": "query",
            "schema": {
              "type": "integer",
              "format": "int32"
            }
          }
        ],
        "responses": {
          "200": {
            "description": "OK"
          }
        }
      }
    }
  },
  "components": {
    "schemas": {
      "AboutMe": {
        "type": "object",
        "properties": {
          "aboutMeId": {
            "type": "integer",
            "format": "int32"
          },
          "fullName": {
            "type": "string",
            "nullable": true
          },
          "title": {
            "type": "string",
            "nullable": true
          },
          "description": {
            "type": "string",
            "nullable": true
          },
          "profileImageUrl": {
            "type": "string",
            "nullable": true
          },
          "location": {
            "type": "string",
            "nullable": true
          },
          "email": {
            "type": "string",
            "nullable": true
          },
          "skills": {
            "type": "array",
            "items": {
              "type": "string"
            },
            "nullable": true
          }
        },
        "additionalProperties": false
      },
      "Education": {
        "type": "object",
        "properties": {
          "educationId": {
            "type": "integer",
            "format": "int32"
          },
          "schoolName": {
            "type": "string",
            "nullable": true
          },
          "degree": {
            "type": "string",
            "nullable": true
          },
          "fieldOfStudy": {
            "type": "string",
            "nullable": true
          },
          "startDate": {
            "type": "string",
            "format": "date-time"
          },
          "endDate": {
            "type": "string",
            "format": "date-time",
            "nullable": true
          },
          "description": {
            "type": "string",
            "nullable": true
          }
        },
        "additionalProperties": false
      }
    }
  }
}